{"cameraMode":{"drawMode":0,"name":"Shaded","section":"Shading Mode"},"sceneLighting":true,"audioPlay":false,"sceneViewState":{"showFog":true,"showMaterialUpdate":false,"showSkybox":true,"showFlares":true,"showImageEffects":true,"showParticleSystems":true},"in2DMode":false,"pivot":{"x":-2.906043529510498,"y":-24.897186279296876,"z":25.958091735839845},"rotation":{"x":0.30552923679351809,"y":0.0057134167291224,"z":-0.001833112328313291,"w":0.952165424823761},"size":51.88861083984375,"orthographic":false}